forgebox/__init__.py
forgebox/batcher.py
forgebox/category.py
forgebox/config.py
forgebox/cosine.py
forgebox/df.py
forgebox/files.py
forgebox/filter_df.py
forgebox/html.py
forgebox/imports.py
forgebox/pd_plus.py
forgebox/treehot.py
forgebox/unpack.py
forgebox/widgets.py
forgebox/wildtree.py
forgebox/ftorch/__init__.py
forgebox/ftorch/cuda.py
forgebox/ftorch/metrics.py
forgebox/ftorch/optimizer.py
forgebox/ftorch/prepro.py
forgebox/images/__init__.py
forgebox/images/widgets.py
forgebox/layers/__init__.py
forgebox/layers/activations.py
forgebox/layers/cv.py
forgebox/layers/nlp.py
forgebox/layers/norm.py
forgebox/static/edit.js
forgebox/static/kingdom.js
forgebox/static/table.html
forgebox/static/workspace.html
forgebox/static/mlm/visual.html
forgebox/static/mlm/visual.js
forgebox/thunder/__init__.py
forgebox/thunder/callbacks.py
forgebox-1.0.9.dist-info/LICENSE
forgebox-1.0.9.dist-info/METADATA
forgebox-1.0.9.dist-info/WHEEL
forgebox-1.0.9.dist-info/top_level.txt
forgebox-1.0.9.dist-info/RECORD
