Metadata-Version: 2.1
Name: forgebox
Version: 1.0.9
Home-page: https://github.com/raynardj/forgebox
License: GPLv3+
Project-URL: Documentation, https://github/raynardj/forgebox/
Project-URL: Tracker, https://github.com/raynardj/forgebox/issues
Classifier: Development Status :: 3 - Alpha
Classifier: Intended Audience :: Developers
Classifier: License :: OSI Approved :: GNU General Public License v3 (GPLv3)
Classifier: Natural Language :: English
Classifier: Programming Language :: Python :: 3.6
Classifier: Programming Language :: Python :: 3.7
Classifier: Programming Language :: Python :: 3.8
Classifier: Programming Language :: Python :: 3.9
Classifier: Programming Language :: Python :: 3.10
Requires-Python: >=3.6
License-File: LICENSE
Requires-Dist: category (>=0.1.0)
